[
  {
    "topic": [
      {
        "id": "5e3e6ee0-f3f1-4d48-a514-408acf829f67",
        "name": "Technology",
        "created_at": "2023-09-09T21:37:47.584Z",
        "updated_at": "2023-09-09T13:31:50.331Z",
        "organization_id": "main_entity_pk"
      },
      {
        "id": "78c4f736-c2e9-40d1-af42-e7c88f34f115",
        "name": "Environment",
        "created_at": "2023-09-09T05:36:44.127Z",
        "updated_at": "2023-09-09T22:03:12.405Z",
        "organization_id": "main_entity_pk"
      },
      {
        "id": "b5365c3a-8413-4e9e-817b-a37142e31f58",
        "name": "Education",
        "created_at": "2023-09-09T10:20:30.701Z",
        "updated_at": "2023-09-09T21:56:47.578Z",
        "organization_id": "main_entity_pk"
      },
      {
        "id": "0ddea21d-5659-4ab5-9abd-20a19fa1b8e0",
        "name": "Healthcare",
        "created_at": "2023-09-10T00:48:16.693Z",
        "updated_at": "2023-09-10T00:50:27.991Z",
        "organization_id": "main_entity_pk"
      },
      {
        "id": "618f4acb-d913-4b35-a3c7-25e8f2b5a2d4",
        "name": "Business",
        "created_at": "2023-09-09T05:22:43.931Z",
        "updated_at": "2023-09-09T04:45:05.551Z",
        "organization_id": "main_entity_pk"
      }
    ],
    "question_generation": [
      {
        "id": "6724b653-1820-4808-9101-956ad318967d",
        "number_of_questions": 70013,
        "created_at": "2023-09-09T23:57:38.969Z",
        "updated_at": "2023-09-09T07:51:52.836Z",
        "topic_id": "0ddea21d-5659-4ab5-9abd-20a19fa1b8e0",
        "user_id": "user_entity_pk"
      },
      {
        "id": "f0878386-83bb-4eaa-867a-d254ca90c2d0",
        "number_of_questions": 95032,
        "created_at": "2023-09-09T04:24:52.347Z",
        "updated_at": "2023-09-10T00:12:51.655Z",
        "topic_id": "78c4f736-c2e9-40d1-af42-e7c88f34f115",
        "user_id": "user_entity_pk"
      },
      {
        "id": "e540d13e-e04d-428f-a4a5-8a95b1b87850",
        "number_of_questions": 67180,
        "created_at": "2023-09-09T21:48:36.635Z",
        "updated_at": "2023-09-09T19:38:17.021Z",
        "topic_id": "5e3e6ee0-f3f1-4d48-a514-408acf829f67",
        "user_id": "user_entity_pk"
      },
      {
        "id": "9df8b5d6-e423-4818-98e4-522de4791b88",
        "number_of_questions": 5445,
        "created_at": "2023-09-09T07:58:12.882Z",
        "updated_at": "2023-09-09T18:34:36.877Z",
        "topic_id": "0ddea21d-5659-4ab5-9abd-20a19fa1b8e0",
        "user_id": "user_entity_pk"
      },
      {
        "id": "ac856558-65e1-47e3-a001-0dcb0017360c",
        "number_of_questions": 68516,
        "created_at": "2023-09-09T12:15:52.558Z",
        "updated_at": "2023-09-09T13:29:23.629Z",
        "topic_id": "78c4f736-c2e9-40d1-af42-e7c88f34f115",
        "user_id": "user_entity_pk"
      }
    ],
    "template": [
      {
        "id": "aa281fa9-46eb-4e5f-a1bb-28feef6c23e8",
        "name": "Welcome Email",
        "content": "Thank you for joining our platform!",
        "created_at": "2023-09-09T14:52:27.577Z",
        "updated_at": "2023-09-10T00:55:25.987Z",
        "organization_id": "main_entity_pk"
      },
      {
        "id": "c42b1601-668a-4f89-b1e6-2c942649af9c",
        "name": "Invoice Template",
        "content": "Please find attached the invoice for your recent purchase.",
        "created_at": "2023-09-09T14:21:12.785Z",
        "updated_at": "2023-09-09T20:41:06.951Z",
        "organization_id": "main_entity_pk"
      },
      {
        "id": "dfef7321-21bb-4f37-9d0a-795f85d68ce8",
        "name": "Meeting Agenda",
        "content": "Agenda for the upcoming team meeting.",
        "created_at": "2023-09-09T05:17:41.426Z",
        "updated_at": "2023-09-09T23:11:23.119Z",
        "organization_id": "main_entity_pk"
      },
      {
        "id": "ab61b81c-d88b-4121-884e-c96ac78e4134",
        "name": "Job Application Form",
        "content": "Please fill out the attached job application form.",
        "created_at": "2023-09-09T10:30:01.441Z",
        "updated_at": "2023-09-09T10:17:06.030Z",
        "organization_id": "main_entity_pk"
      },
      {
        "id": "a14bec4b-9ccb-4434-83d4-776905f18939",
        "name": "Product Catalog",
        "content": "Check out our latest product catalog for exciting offers!",
        "created_at": "2023-09-09T20:40:57.522Z",
        "updated_at": "2023-09-09T21:43:26.722Z",
        "organization_id": "main_entity_pk"
      }
    ],
    "question": [
      {
        "id": "094a86ce-4556-4eb0-b59d-1e314de46f8e",
        "content": "What is your favorite book?",
        "question_topic": "Books",
        "created_at": "2023-09-09T19:51:33.920Z",
        "updated_at": "2023-09-09T20:53:35.141Z",
        "template_id": "c42b1601-668a-4f89-b1e6-2c942649af9c"
      },
      {
        "id": "93fe9e73-80f6-4203-be22-dadaf47fbe66",
        "content": "How can we improve our customer service?",
        "question_topic": "Customer Service",
        "created_at": "2023-09-09T13:49:15.786Z",
        "updated_at": "2023-09-09T14:04:33.693Z",
        "template_id": "aa281fa9-46eb-4e5f-a1bb-28feef6c23e8"
      },
      {
        "id": "24e3a9d8-9d66-4023-8e9d-a2369cc8e3f0",
        "content": "What are your career goals?",
        "question_topic": "Career Development",
        "created_at": "2023-09-09T04:36:46.867Z",
        "updated_at": "2023-09-09T16:04:50.968Z",
        "template_id": "dfef7321-21bb-4f37-9d0a-795f85d68ce8"
      },
      {
        "id": "402085bc-3555-4d64-8a6e-90c52bf75e47",
        "content": "What is your opinion on climate change?",
        "question_topic": "Climate Change",
        "created_at": "2023-09-09T20:26:41.281Z",
        "updated_at": "2023-09-09T07:29:50.883Z",
        "template_id": "a14bec4b-9ccb-4434-83d4-776905f18939"
      },
      {
        "id": "6628892f-8167-4b3f-bd41-3f717452ebaa",
        "content": "How do you define success?",
        "question_topic": "Success",
        "created_at": "2023-09-09T08:36:51.318Z",
        "updated_at": "2023-09-10T03:09:10.667Z",
        "template_id": "aa281fa9-46eb-4e5f-a1bb-28feef6c23e8"
      }
    ],
    "roqUser": [
      {
        "reference": "f17a1464-d521-41ac-8b5d-9d661ba9851f",
        "email": "Hugh11@gmail.com",
        "firstName": "Granville",
        "lastName": "Mante",
        "active": true,
        "avatarUrl": "https://cloudflare-ipfs.com/ipfs/Qmd3W5DuhgHirLHGVixi6V76LhCkZUz6pnFt5AJBiyvHye/avatar/1192.jpg",
        "tenantId": null
      },
      {
        "reference": "0d844205-30b7-4733-bfd4-87a3b0ca220c",
        "email": "Augustus.Tremblay63@yahoo.com",
        "firstName": "Ariane",
        "lastName": "Bode",
        "active": true,
        "avatarUrl": "https://avatars.githubusercontent.com/u/14378861",
        "tenantId": null
      },
      {
        "reference": "84b38acb-3b28-4a3f-9cc2-07a00d5d15e2",
        "email": "Tyra1@hotmail.com",
        "firstName": "Carroll",
        "lastName": "Daugherty",
        "active": true,
        "avatarUrl": "https://cloudflare-ipfs.com/ipfs/Qmd3W5DuhgHirLHGVixi6V76LhCkZUz6pnFt5AJBiyvHye/avatar/298.jpg",
        "tenantId": null
      },
      {
        "reference": "272a98d1-bbfd-42d9-90cc-20eb78d4ac60",
        "email": "Brandyn25@yahoo.com",
        "firstName": "Demond",
        "lastName": "Boyer",
        "active": true,
        "avatarUrl": "https://cloudflare-ipfs.com/ipfs/Qmd3W5DuhgHirLHGVixi6V76LhCkZUz6pnFt5AJBiyvHye/avatar/1107.jpg",
        "tenantId": null
      },
      {
        "reference": "c660e4fd-cbd0-49d4-9e9d-1b9937d2a904",
        "email": "Abelardo.Kuhic@hotmail.com",
        "firstName": "Jaeden",
        "lastName": "Kohler",
        "active": true,
        "avatarUrl": "https://avatars.githubusercontent.com/u/30711529",
        "tenantId": null
      }
    ]
  },
  {
    "topic": [
      {
        "id": "4ded094f-f059-44c8-9120-03806c4bc699",
        "name": "Technology",
        "created_at": "2023-09-09T06:36:22.193Z",
        "updated_at": "2023-09-09T11:19:10.244Z",
        "organization_id": "main_entity_pk"
      },
      {
        "id": "9495e1dd-c919-44a6-bf32-d4931308124b",
        "name": "Environment",
        "created_at": "2023-09-10T01:36:14.548Z",
        "updated_at": "2023-09-10T01:56:57.838Z",
        "organization_id": "main_entity_pk"
      },
      {
        "id": "9740bb89-352a-41fa-8b09-b5493362e225",
        "name": "Business",
        "created_at": "2023-09-09T07:45:41.506Z",
        "updated_at": "2023-09-10T02:00:28.747Z",
        "organization_id": "main_entity_pk"
      },
      {
        "id": "da1d72f0-757a-4b11-b5d9-f6605c93f09c",
        "name": "Healthcare",
        "created_at": "2023-09-09T16:23:54.923Z",
        "updated_at": "2023-09-09T22:20:41.091Z",
        "organization_id": "main_entity_pk"
      },
      {
        "id": "62a87f93-6a0e-461d-95a6-8016a40c12a9",
        "name": "Education",
        "created_at": "2023-09-09T11:09:06.179Z",
        "updated_at": "2023-09-09T08:25:18.347Z",
        "organization_id": "main_entity_pk"
      }
    ],
    "question_generation": [
      {
        "id": "11a02ec4-628b-48cc-881a-ed8142b0b890",
        "number_of_questions": 22968,
        "created_at": "2023-09-09T18:44:32.889Z",
        "updated_at": "2023-09-09T08:23:36.152Z",
        "topic_id": "4ded094f-f059-44c8-9120-03806c4bc699",
        "user_id": "user_entity_pk"
      },
      {
        "id": "191c2d84-ee42-4938-8409-622ac7717d80",
        "number_of_questions": 43822,
        "created_at": "2023-09-09T04:33:20.731Z",
        "updated_at": "2023-09-09T13:34:03.783Z",
        "topic_id": "62a87f93-6a0e-461d-95a6-8016a40c12a9",
        "user_id": "user_entity_pk"
      },
      {
        "id": "066ff597-21af-4f57-8881-afb103d37bd7",
        "number_of_questions": 43372,
        "created_at": "2023-09-09T21:57:14.328Z",
        "updated_at": "2023-09-10T02:51:43.400Z",
        "topic_id": "62a87f93-6a0e-461d-95a6-8016a40c12a9",
        "user_id": "user_entity_pk"
      },
      {
        "id": "af81d7be-d9f2-46cf-92b1-038dd405e426",
        "number_of_questions": 93370,
        "created_at": "2023-09-09T23:17:44.730Z",
        "updated_at": "2023-09-09T04:28:15.806Z",
        "topic_id": "da1d72f0-757a-4b11-b5d9-f6605c93f09c",
        "user_id": "user_entity_pk"
      },
      {
        "id": "fe9f243d-e2d5-47a9-b400-2f83028a5967",
        "number_of_questions": 64179,
        "created_at": "2023-09-09T14:46:24.067Z",
        "updated_at": "2023-09-09T22:47:52.219Z",
        "topic_id": "62a87f93-6a0e-461d-95a6-8016a40c12a9",
        "user_id": "user_entity_pk"
      }
    ],
    "template": [
      {
        "id": "4dfe9e84-d407-4e65-b0a2-4cdd963785da",
        "name": "Welcome Email",
        "content": "Dear {firstName},\n\nWelcome to our platform!",
        "created_at": "2023-09-09T08:52:49.855Z",
        "updated_at": "2023-09-09T14:21:46.784Z",
        "organization_id": "main_entity_pk"
      },
      {
        "id": "96730a2a-5bb3-4a73-9864-9f9425fb5126",
        "name": "Invoice Template",
        "content": "Invoice for services rendered:\n\n{content}",
        "created_at": "2023-09-09T07:16:16.566Z",
        "updated_at": "2023-09-09T16:41:31.969Z",
        "organization_id": "main_entity_pk"
      },
      {
        "id": "d5ad348a-ed9c-4a6a-a476-2d743a22b479",
        "name": "Meeting Agenda",
        "content": "Agenda for the upcoming meeting:\n\n{content}",
        "created_at": "2023-09-09T09:28:35.887Z",
        "updated_at": "2023-09-09T04:59:55.030Z",
        "organization_id": "main_entity_pk"
      },
      {
        "id": "a07e376c-001e-4fc7-95bb-8937e0070a0a",
        "name": "Job Application Form",
        "content": "Please fill out the job application form attached.",
        "created_at": "2023-09-09T10:21:56.659Z",
        "updated_at": "2023-09-09T13:35:23.575Z",
        "organization_id": "main_entity_pk"
      },
      {
        "id": "069aca89-ed46-4d89-b13e-a8b0fb55fdb2",
        "name": "Feedback Survey",
        "content": "We value your feedback. Please take a moment to complete our survey.",
        "created_at": "2023-09-09T09:53:59.160Z",
        "updated_at": "2023-09-10T02:44:14.957Z",
        "organization_id": "main_entity_pk"
      }
    ],
    "question": [
      {
        "id": "7cde24ef-0455-4877-b935-e559c2c866a7",
        "content": "What is your favorite book?",
        "question_topic": "Books",
        "created_at": "2023-09-09T14:31:24.379Z",
        "updated_at": "2023-09-09T13:05:21.020Z",
        "template_id": "4dfe9e84-d407-4e65-b0a2-4cdd963785da"
      },
      {
        "id": "77e63579-f864-4e7e-a45d-7df0c9f9c35e",
        "content": "How do you define success?",
        "question_topic": "Success",
        "created_at": "2023-09-09T20:51:31.981Z",
        "updated_at": "2023-09-10T01:27:12.662Z",
        "template_id": "069aca89-ed46-4d89-b13e-a8b0fb55fdb2"
      },
      {
        "id": "a2306b3c-d1e3-4cf6-a5bd-3c38977f9208",
        "content": "What are your career goals?",
        "question_topic": "Career",
        "created_at": "2023-09-09T07:39:56.793Z",
        "updated_at": "2023-09-09T06:37:56.298Z",
        "template_id": "d5ad348a-ed9c-4a6a-a476-2d743a22b479"
      },
      {
        "id": "a1f15b23-45a6-4e53-9f99-b4edf6278acc",
        "content": "What is your opinion on climate change?",
        "question_topic": "Climate Change",
        "created_at": "2023-09-09T09:14:54.355Z",
        "updated_at": "2023-09-09T20:03:54.492Z",
        "template_id": "96730a2a-5bb3-4a73-9864-9f9425fb5126"
      },
      {
        "id": "594fd0dd-4ab3-4b55-b46a-f25c4745be54",
        "content": "How do you handle stress?",
        "question_topic": "Stress Management",
        "created_at": "2023-09-09T05:12:59.472Z",
        "updated_at": "2023-09-09T23:26:12.063Z",
        "template_id": "4dfe9e84-d407-4e65-b0a2-4cdd963785da"
      }
    ],
    "roqUser": [
      {
        "reference": "046d14b5-3ad5-4538-ab2f-13ba8e49c6da",
        "email": "Emie.Bahringer78@gmail.com",
        "firstName": "Krystal",
        "lastName": "Medhurst",
        "active": true,
        "avatarUrl": "https://cloudflare-ipfs.com/ipfs/Qmd3W5DuhgHirLHGVixi6V76LhCkZUz6pnFt5AJBiyvHye/avatar/635.jpg",
        "tenantId": null
      },
      {
        "reference": "c3b38ca6-2264-4979-9f2f-379d6222fa61",
        "email": "Cassandra.Anderson@gmail.com",
        "firstName": "Kathlyn",
        "lastName": "Carroll",
        "active": true,
        "avatarUrl": "https://avatars.githubusercontent.com/u/67437394",
        "tenantId": null
      },
      {
        "reference": "b673f006-4b6f-4130-a9e5-7f91e0a8711f",
        "email": "Meta86@hotmail.com",
        "firstName": "Emma",
        "lastName": "Wisozk",
        "active": true,
        "avatarUrl": "https://cloudflare-ipfs.com/ipfs/Qmd3W5DuhgHirLHGVixi6V76LhCkZUz6pnFt5AJBiyvHye/avatar/906.jpg",
        "tenantId": null
      },
      {
        "reference": "8d5ae18c-0620-41cc-9cbd-21eea422bbaa",
        "email": "Dolores.Mraz74@gmail.com",
        "firstName": "Lucinda",
        "lastName": "Littel",
        "active": true,
        "avatarUrl": "https://cloudflare-ipfs.com/ipfs/Qmd3W5DuhgHirLHGVixi6V76LhCkZUz6pnFt5AJBiyvHye/avatar/793.jpg",
        "tenantId": null
      },
      {
        "reference": "4568c406-ebb9-43b8-992f-3a7706a7057e",
        "email": "Raleigh60@hotmail.com",
        "firstName": "Briana",
        "lastName": "Christiansen",
        "active": true,
        "avatarUrl": "https://avatars.githubusercontent.com/u/44352375",
        "tenantId": null
      }
    ]
  },
  {
    "topic": [
      {
        "id": "c82985a1-23e8-4f2d-ad07-c4baeed9b760",
        "name": "Science",
        "created_at": "2023-09-09T23:21:29.279Z",
        "updated_at": "2023-09-09T20:32:05.760Z",
        "organization_id": "main_entity_pk"
      },
      {
        "id": "75f76e4e-f721-4a22-b938-b945caf57e12",
        "name": "Technology",
        "created_at": "2023-09-09T23:47:16.829Z",
        "updated_at": "2023-09-09T23:04:30.368Z",
        "organization_id": "main_entity_pk"
      },
      {
        "id": "1d141f26-087b-476c-aaa2-daab3cdab77f",
        "name": "Art",
        "created_at": "2023-09-09T04:05:34.454Z",
        "updated_at": "2023-09-09T10:34:33.874Z",
        "organization_id": "main_entity_pk"
      },
      {
        "id": "678231b4-56ca-4d9e-ad5c-7b133f1b9a5e",
        "name": "Sports",
        "created_at": "2023-09-09T20:18:23.354Z",
        "updated_at": "2023-09-09T18:25:46.550Z",
        "organization_id": "main_entity_pk"
      },
      {
        "id": "a4e39af7-e220-4ede-8213-60eacf29ea62",
        "name": "History",
        "created_at": "2023-09-09T08:55:50.572Z",
        "updated_at": "2023-09-09T22:00:32.141Z",
        "organization_id": "main_entity_pk"
      }
    ],
    "question_generation": [
      {
        "id": "156ddfe5-d0d8-45f0-b910-3ec44f6517b9",
        "number_of_questions": 52107,
        "created_at": "2023-09-09T23:29:08.929Z",
        "updated_at": "2023-09-09T20:50:55.028Z",
        "topic_id": "678231b4-56ca-4d9e-ad5c-7b133f1b9a5e",
        "user_id": "user_entity_pk"
      },
      {
        "id": "947197c8-4aec-486c-baa3-2ee0a578fadb",
        "number_of_questions": 59470,
        "created_at": "2023-09-09T11:58:12.626Z",
        "updated_at": "2023-09-09T12:06:23.172Z",
        "topic_id": "1d141f26-087b-476c-aaa2-daab3cdab77f",
        "user_id": "user_entity_pk"
      },
      {
        "id": "a53e383c-0b0a-4fb9-8605-971aa33212cc",
        "number_of_questions": 80629,
        "created_at": "2023-09-09T10:56:44.306Z",
        "updated_at": "2023-09-09T11:10:12.508Z",
        "topic_id": "c82985a1-23e8-4f2d-ad07-c4baeed9b760",
        "user_id": "user_entity_pk"
      },
      {
        "id": "43ddf74f-5683-4139-b6d3-1214a32a66b6",
        "number_of_questions": 39621,
        "created_at": "2023-09-10T02:50:17.102Z",
        "updated_at": "2023-09-10T02:12:12.814Z",
        "topic_id": "c82985a1-23e8-4f2d-ad07-c4baeed9b760",
        "user_id": "user_entity_pk"
      },
      {
        "id": "a5c5c583-45c0-422c-a83b-343e731b7c23",
        "number_of_questions": 76574,
        "created_at": "2023-09-09T05:24:26.777Z",
        "updated_at": "2023-09-09T14:40:48.439Z",
        "topic_id": "1d141f26-087b-476c-aaa2-daab3cdab77f",
        "user_id": "user_entity_pk"
      }
    ],
    "template": [
      {
        "id": "857d7f8d-e5ed-4103-bf8f-b4e2a4d07b47",
        "name": "Welcome Email",
        "content": "Thank you for joining us! We are excited to have you on board.",
        "created_at": "2023-09-09T07:42:00.930Z",
        "updated_at": "2023-09-09T19:23:44.114Z",
        "organization_id": "main_entity_pk"
      },
      {
        "id": "41dcdf0b-39f5-405c-b021-15487007b9ce",
        "name": "Invoice",
        "content": "Please find attached the invoice for your recent purchase.",
        "created_at": "2023-09-09T21:29:23.714Z",
        "updated_at": "2023-09-09T07:28:04.447Z",
        "organization_id": "main_entity_pk"
      },
      {
        "id": "deca5b2a-1ce9-4717-a0a7-0dc566179c18",
        "name": "Newsletter",
        "content": "Stay updated with our latest news and updates.",
        "created_at": "2023-09-09T10:44:31.716Z",
        "updated_at": "2023-09-09T23:04:07.938Z",
        "organization_id": "main_entity_pk"
      },
      {
        "id": "1a5c3498-7e8c-4f21-a450-8468c06836b5",
        "name": "Meeting Agenda",
        "content": "Agenda for the upcoming team meeting.",
        "created_at": "2023-09-09T08:01:21.624Z",
        "updated_at": "2023-09-10T00:21:48.545Z",
        "organization_id": "main_entity_pk"
      },
      {
        "id": "2852d609-b6c3-4784-b28e-16afdcef07e6",
        "name": "Job Application",
        "content": "Apply now for the open position at our company.",
        "created_at": "2023-09-09T06:18:53.777Z",
        "updated_at": "2023-09-09T08:25:56.865Z",
        "organization_id": "main_entity_pk"
      }
    ],
    "question": [
      {
        "id": "39280a05-981c-4488-b3d2-3bc205b9cde5",
        "content": "What is your favorite color?",
        "question_topic": "Personal",
        "created_at": "2023-09-09T14:24:37.828Z",
        "updated_at": "2023-09-09T04:53:00.167Z",
        "template_id": "2852d609-b6c3-4784-b28e-16afdcef07e6"
      },
      {
        "id": "b8fccf13-f541-4ea1-b6d6-77ae3bebc97e",
        "content": "How do you define success?",
        "question_topic": "Career",
        "created_at": "2023-09-09T07:18:54.472Z",
        "updated_at": "2023-09-09T07:48:51.280Z",
        "template_id": "41dcdf0b-39f5-405c-b021-15487007b9ce"
      },
      {
        "id": "9973c3f9-17db-4fa6-baaa-86f4ecbe953d",
        "content": "What are your hobbies?",
        "question_topic": "Interests",
        "created_at": "2023-09-09T21:08:34.471Z",
        "updated_at": "2023-09-09T19:44:49.859Z",
        "template_id": "857d7f8d-e5ed-4103-bf8f-b4e2a4d07b47"
      },
      {
        "id": "fdccf56e-dca0-4042-b55d-8edc6c6715ad",
        "content": "What is your favorite book?",
        "question_topic": "Literature",
        "created_at": "2023-09-09T12:24:05.446Z",
        "updated_at": "2023-09-09T06:05:24.646Z",
        "template_id": "857d7f8d-e5ed-4103-bf8f-b4e2a4d07b47"
      },
      {
        "id": "4ab2f5d9-b8b4-489e-aab1-43a92681bba5",
        "content": "Tell us about a challenging situation you faced and how you overcame it.",
        "question_topic": "Problem Solving",
        "created_at": "2023-09-09T05:46:36.935Z",
        "updated_at": "2023-09-09T08:48:17.825Z",
        "template_id": "deca5b2a-1ce9-4717-a0a7-0dc566179c18"
      }
    ],
    "roqUser": [
      {
        "reference": "db75120b-ee64-4f93-b7b4-f0c90287b556",
        "email": "Elvis_Spencer82@gmail.com",
        "firstName": "Alaina",
        "lastName": "Terry",
        "active": true,
        "avatarUrl": "https://avatars.githubusercontent.com/u/35225844",
        "tenantId": null
      },
      {
        "reference": "e401a4c0-470a-4f09-81b5-d71766c393c3",
        "email": "Ruben.Moore54@yahoo.com",
        "firstName": "Elta",
        "lastName": "Schaefer",
        "active": true,
        "avatarUrl": "https://avatars.githubusercontent.com/u/43052609",
        "tenantId": null
      },
      {
        "reference": "89c58319-a061-42b3-844d-014f9202f87b",
        "email": "Lilla.McGlynn@hotmail.com",
        "firstName": "Kailyn",
        "lastName": "Smitham",
        "active": true,
        "avatarUrl": "https://cloudflare-ipfs.com/ipfs/Qmd3W5DuhgHirLHGVixi6V76LhCkZUz6pnFt5AJBiyvHye/avatar/1216.jpg",
        "tenantId": null
      },
      {
        "reference": "67f542ec-bbd5-44db-b519-4d1d24388172",
        "email": "Izaiah.Witting@gmail.com",
        "firstName": "Christiana",
        "lastName": "Schaefer",
        "active": true,
        "avatarUrl": "https://cloudflare-ipfs.com/ipfs/Qmd3W5DuhgHirLHGVixi6V76LhCkZUz6pnFt5AJBiyvHye/avatar/684.jpg",
        "tenantId": null
      },
      {
        "reference": "e3df3d7d-dc04-43cf-b9ee-111ad7a45448",
        "email": "Lottie91@gmail.com",
        "firstName": "Ashleigh",
        "lastName": "Murazik",
        "active": true,
        "avatarUrl": "https://cloudflare-ipfs.com/ipfs/Qmd3W5DuhgHirLHGVixi6V76LhCkZUz6pnFt5AJBiyvHye/avatar/1161.jpg",
        "tenantId": null
      }
    ]
  },
  {
    "topic": [
      {
        "id": "6be01d36-cbb0-489a-bf40-c39ac6921ad8",
        "name": "Technology",
        "created_at": "2023-09-10T02:54:47.261Z",
        "updated_at": "2023-09-10T02:37:21.359Z",
        "organization_id": "main_entity_pk"
      },
      {
        "id": "8d331da6-d5c8-43e0-a759-24e98bab907d",
        "name": "Science",
        "created_at": "2023-09-09T15:53:43.153Z",
        "updated_at": "2023-09-09T16:30:24.101Z",
        "organization_id": "main_entity_pk"
      },
      {
        "id": "5cbd0621-51d9-4f81-8ccb-459290ca0a53",
        "name": "Business",
        "created_at": "2023-09-09T05:46:28.588Z",
        "updated_at": "2023-09-09T18:17:37.587Z",
        "organization_id": "main_entity_pk"
      },
      {
        "id": "6a863761-a2a3-4027-952a-cf1470da17ff",
        "name": "Art",
        "created_at": "2023-09-10T01:51:40.620Z",
        "updated_at": "2023-09-09T07:53:28.675Z",
        "organization_id": "main_entity_pk"
      },
      {
        "id": "f3458912-2a2f-4975-b3c5-754f2ddf1e30",
        "name": "Sports",
        "created_at": "2023-09-09T14:17:33.338Z",
        "updated_at": "2023-09-09T20:36:53.540Z",
        "organization_id": "main_entity_pk"
      }
    ],
    "question_generation": [
      {
        "id": "7dd0a25a-9ef2-4c35-bf38-7cd74abdb3a3",
        "number_of_questions": 9656,
        "created_at": "2023-09-10T02:31:35.983Z",
        "updated_at": "2023-09-10T01:43:20.365Z",
        "topic_id": "6be01d36-cbb0-489a-bf40-c39ac6921ad8",
        "user_id": "user_entity_pk"
      },
      {
        "id": "a75f093a-da97-411f-a3e0-dcf7122b98ec",
        "number_of_questions": 41342,
        "created_at": "2023-09-09T12:34:24.001Z",
        "updated_at": "2023-09-09T07:37:54.664Z",
        "topic_id": "5cbd0621-51d9-4f81-8ccb-459290ca0a53",
        "user_id": "user_entity_pk"
      },
      {
        "id": "35063fe1-bfc3-41ab-ac74-7018e10ccedf",
        "number_of_questions": 71532,
        "created_at": "2023-09-09T09:42:56.379Z",
        "updated_at": "2023-09-10T00:23:01.774Z",
        "topic_id": "6a863761-a2a3-4027-952a-cf1470da17ff",
        "user_id": "user_entity_pk"
      },
      {
        "id": "a24e4fb8-b683-46fb-9999-4a05976d21fc",
        "number_of_questions": 94251,
        "created_at": "2023-09-09T12:41:56.287Z",
        "updated_at": "2023-09-09T07:58:02.280Z",
        "topic_id": "f3458912-2a2f-4975-b3c5-754f2ddf1e30",
        "user_id": "user_entity_pk"
      },
      {
        "id": "940e781d-1c38-4c28-9a60-529b6c068c62",
        "number_of_questions": 882,
        "created_at": "2023-09-09T20:31:09.865Z",
        "updated_at": "2023-09-09T12:28:27.107Z",
        "topic_id": "5cbd0621-51d9-4f81-8ccb-459290ca0a53",
        "user_id": "user_entity_pk"
      }
    ],
    "template": [
      {
        "id": "6ddb5caa-6927-44f2-854f-9d0ba5d07908",
        "name": "Welcome Email",
        "content": "Dear [firstName],\n\nThank you for joining our platform.\n\nBest regards,\n[organizationName]",
        "created_at": "2023-09-09T07:57:58.481Z",
        "updated_at": "2023-09-09T20:55:15.251Z",
        "organization_id": "main_entity_pk"
      },
      {
        "id": "5d2f9d06-d7c1-4265-bf67-d9067ad86397",
        "name": "Newsletter",
        "content": "Hello,\n\nHere are the latest updates from our organization.\n\nRegards,\n[organizationName]",
        "created_at": "2023-09-09T15:48:06.874Z",
        "updated_at": "2023-09-09T21:23:24.270Z",
        "organization_id": "main_entity_pk"
      },
      {
        "id": "77a48dfe-7aaa-4007-b71d-3f9d1ff937f9",
        "name": "Invoice",
        "content": "Invoice\n\nAmount: $100\nDue Date: [dueDate]\n\nRegards,\n[organizationName]",
        "created_at": "2023-09-09T05:02:00.175Z",
        "updated_at": "2023-09-09T23:00:50.605Z",
        "organization_id": "main_entity_pk"
      },
      {
        "id": "5faf95ed-9a74-42cd-bf14-132a9307f086",
        "name": "Meeting Agenda",
        "content": "Meeting Agenda\n\nDate: [meetingDate]\nLocation: [meetingLocation]\n\nRegards,\n[organizationName]",
        "created_at": "2023-09-09T21:55:23.852Z",
        "updated_at": "2023-09-09T12:32:36.337Z",
        "organization_id": "main_entity_pk"
      },
      {
        "id": "8f5fe462-6a2c-43d9-85d8-0eb76015841b",
        "name": "Job Application",
        "content": "Job Application\n\nPosition: [position]\nExperience: [experience]\n\nRegards,\n[organizationName]",
        "created_at": "2023-09-09T06:41:59.590Z",
        "updated_at": "2023-09-09T15:12:42.689Z",
        "organization_id": "main_entity_pk"
      }
    ],
    "question": [
      {
        "id": "cb10ed6d-8731-4097-ac3c-570ce43be4d7",
        "content": "How can I improve my programming skills?",
        "question_topic": "Education",
        "created_at": "2023-09-10T01:34:08.141Z",
        "updated_at": "2023-09-09T08:30:09.618Z",
        "template_id": "6ddb5caa-6927-44f2-854f-9d0ba5d07908"
      },
      {
        "id": "48ce3ffe-75a8-4768-9ade-ec26871efa5f",
        "content": "What are the benefits of exercise?",
        "question_topic": "Health",
        "created_at": "2023-09-09T04:54:59.474Z",
        "updated_at": "2023-09-10T01:28:26.393Z",
        "template_id": "8f5fe462-6a2c-43d9-85d8-0eb76015841b"
      },
      {
        "id": "75bbd1d5-a8f4-4add-b8e2-9a3f25a72c0d",
        "content": "How can I start my own business?",
        "question_topic": "Business",
        "created_at": "2023-09-09T08:44:57.978Z",
        "updated_at": "2023-09-09T17:05:54.463Z",
        "template_id": "5faf95ed-9a74-42cd-bf14-132a9307f086"
      },
      {
        "id": "2d6c061e-e7f2-4baa-819c-cc0a31193459",
        "content": "What is the best way to learn a new language?",
        "question_topic": "Language Learning",
        "created_at": "2023-09-09T08:36:28.472Z",
        "updated_at": "2023-09-09T13:14:50.685Z",
        "template_id": "8f5fe462-6a2c-43d9-85d8-0eb76015841b"
      },
      {
        "id": "db96782d-2af4-41e0-9daa-53dfb789b980",
        "content": "How can I become a better public speaker?",
        "question_topic": "Communication",
        "created_at": "2023-09-09T03:45:35.677Z",
        "updated_at": "2023-09-09T20:01:29.439Z",
        "template_id": "5faf95ed-9a74-42cd-bf14-132a9307f086"
      }
    ],
    "roqUser": [
      {
        "reference": "2924454b-e490-4603-bc0c-f0f48f99246c",
        "email": "Carroll98@hotmail.com",
        "firstName": "Jermey",
        "lastName": "Green-Wuckert",
        "active": true,
        "avatarUrl": "https://avatars.githubusercontent.com/u/84925711",
        "tenantId": null
      },
      {
        "reference": "31c8e84c-ccc0-4939-bb83-e6cedbb49783",
        "email": "Elenor.Botsford70@yahoo.com",
        "firstName": "Delta",
        "lastName": "Botsford",
        "active": true,
        "avatarUrl": "https://cloudflare-ipfs.com/ipfs/Qmd3W5DuhgHirLHGVixi6V76LhCkZUz6pnFt5AJBiyvHye/avatar/610.jpg",
        "tenantId": null
      },
      {
        "reference": "8567245b-e0e8-4eb8-9c43-3300a93765aa",
        "email": "Rebekah.Hackett86@hotmail.com",
        "firstName": "Marjorie",
        "lastName": "VonRueden",
        "active": true,
        "avatarUrl": "https://cloudflare-ipfs.com/ipfs/Qmd3W5DuhgHirLHGVixi6V76LhCkZUz6pnFt5AJBiyvHye/avatar/604.jpg",
        "tenantId": null
      },
      {
        "reference": "692c6fd2-62a5-4a85-a2c8-fbed8c7b5fdd",
        "email": "Elenor52@gmail.com",
        "firstName": "Baron",
        "lastName": "Mosciski",
        "active": true,
        "avatarUrl": "https://cloudflare-ipfs.com/ipfs/Qmd3W5DuhgHirLHGVixi6V76LhCkZUz6pnFt5AJBiyvHye/avatar/63.jpg",
        "tenantId": null
      },
      {
        "reference": "546e3719-4181-4739-8f79-d35dd665e30c",
        "email": "Monty18@gmail.com",
        "firstName": "Breanna",
        "lastName": "Morissette",
        "active": true,
        "avatarUrl": "https://cloudflare-ipfs.com/ipfs/Qmd3W5DuhgHirLHGVixi6V76LhCkZUz6pnFt5AJBiyvHye/avatar/985.jpg",
        "tenantId": null
      }
    ]
  },
  {
    "topic": [
      {
        "id": "95ecaa10-1f3b-4366-b07d-c4fcd3ad0d1f",
        "name": "Technology",
        "created_at": "2023-09-10T00:39:07.878Z",
        "updated_at": "2023-09-09T14:55:03.740Z",
        "organization_id": "main_entity_pk"
      },
      {
        "id": "4c511f45-7d50-4f22-9e27-bc11369538aa",
        "name": "Environment",
        "created_at": "2023-09-09T22:57:49.160Z",
        "updated_at": "2023-09-09T14:17:51.285Z",
        "organization_id": "main_entity_pk"
      },
      {
        "id": "54f2b5ef-115e-431b-adcf-4fee75e74dc2",
        "name": "Business",
        "created_at": "2023-09-09T23:57:18.519Z",
        "updated_at": "2023-09-09T20:11:16.567Z",
        "organization_id": "main_entity_pk"
      },
      {
        "id": "037de05a-e6ef-4765-b6b4-da9e34e868e9",
        "name": "Healthcare",
        "created_at": "2023-09-09T08:12:00.097Z",
        "updated_at": "2023-09-09T19:32:11.476Z",
        "organization_id": "main_entity_pk"
      },
      {
        "id": "89ee8dc3-59c3-417f-8e6c-5e0d7012b09e",
        "name": "Education",
        "created_at": "2023-09-09T07:23:19.660Z",
        "updated_at": "2023-09-09T09:50:45.840Z",
        "organization_id": "main_entity_pk"
      }
    ],
    "question_generation": [
      {
        "id": "c6456f06-f318-485a-9c4d-74e9eedd69a8",
        "number_of_questions": 97173,
        "created_at": "2023-09-10T01:21:36.868Z",
        "updated_at": "2023-09-09T12:50:58.809Z",
        "topic_id": "54f2b5ef-115e-431b-adcf-4fee75e74dc2",
        "user_id": "user_entity_pk"
      },
      {
        "id": "4bfcdf21-97cf-404a-8e33-25b8cf8ae415",
        "number_of_questions": 39529,
        "created_at": "2023-09-09T20:49:03.749Z",
        "updated_at": "2023-09-09T05:58:45.966Z",
        "topic_id": "54f2b5ef-115e-431b-adcf-4fee75e74dc2",
        "user_id": "user_entity_pk"
      },
      {
        "id": "63a79be4-b3e2-47eb-b589-ab801022898a",
        "number_of_questions": 80232,
        "created_at": "2023-09-09T21:19:51.125Z",
        "updated_at": "2023-09-09T04:28:43.803Z",
        "topic_id": "54f2b5ef-115e-431b-adcf-4fee75e74dc2",
        "user_id": "user_entity_pk"
      },
      {
        "id": "ca0755c6-1f3b-47c9-8c69-fa2a862b4c50",
        "number_of_questions": 61582,
        "created_at": "2023-09-09T10:57:30.354Z",
        "updated_at": "2023-09-09T18:44:29.251Z",
        "topic_id": "89ee8dc3-59c3-417f-8e6c-5e0d7012b09e",
        "user_id": "user_entity_pk"
      },
      {
        "id": "95a64cc2-1dc7-484a-80cf-84f802ee7c06",
        "number_of_questions": 50471,
        "created_at": "2023-09-09T14:10:06.954Z",
        "updated_at": "2023-09-09T15:18:07.786Z",
        "topic_id": "89ee8dc3-59c3-417f-8e6c-5e0d7012b09e",
        "user_id": "user_entity_pk"
      }
    ],
    "template": [
      {
        "id": "9e3cc62b-778b-41c7-8be5-783e0ff069fd",
        "name": "Welcome Email",
        "content": "Dear {firstName},\n\nWelcome to our platform!",
        "created_at": "2023-09-10T02:34:14.422Z",
        "updated_at": "2023-09-09T07:23:08.262Z",
        "organization_id": "main_entity_pk"
      },
      {
        "id": "abcb8bd9-1750-4ac5-965d-b87691a6d7ea",
        "name": "Invoice Template",
        "content": "Invoice Number: {randomNumber}\n\nTotal Amount: {randomAmount}",
        "created_at": "2023-09-09T23:30:08.335Z",
        "updated_at": "2023-09-09T06:04:13.902Z",
        "organization_id": "main_entity_pk"
      },
      {
        "id": "1ef663c0-4dad-4bd3-8a46-e6ed0cf13d6c",
        "name": "Meeting Agenda",
        "content": "Agenda for the Meeting on {date}\n\n1. Introduction\n2. Discussion of Project Scope\n3. Q&A Session",
        "created_at": "2023-09-09T15:26:48.758Z",
        "updated_at": "2023-09-09T05:35:47.823Z",
        "organization_id": "main_entity_pk"
      },
      {
        "id": "7d86ae4d-19a5-4fbc-b8ec-11011f724b2f",
        "name": "Job Application Form",
        "content": "Please fill out the following form to apply for the job:\n\nName: {fullName}\nEmail: {email}\nPhone: {phoneNumber}",
        "created_at": "2023-09-09T06:51:21.129Z",
        "updated_at": "2023-09-10T00:14:49.003Z",
        "organization_id": "main_entity_pk"
      },
      {
        "id": "d46dac46-6e87-4b3d-a1bd-f9e1590035dd",
        "name": "Product Catalog",
        "content": "Check out our latest product catalog:\n\n- Product 1\n- Product 2\n- Product 3",
        "created_at": "2023-09-09T04:58:54.772Z",
        "updated_at": "2023-09-09T20:42:49.478Z",
        "organization_id": "main_entity_pk"
      }
    ],
    "question": [
      {
        "id": "b6325686-0b5d-46df-90f0-08d9f9586277",
        "content": "What is your favorite book?",
        "question_topic": "Personal Development",
        "created_at": "2023-09-09T17:00:23.284Z",
        "updated_at": "2023-09-09T08:15:59.827Z",
        "template_id": "1ef663c0-4dad-4bd3-8a46-e6ed0cf13d6c"
      },
      {
        "id": "aae5f86a-8e29-447f-adbd-9d5db2e6e80b",
        "content": "How do you define success?",
        "question_topic": "Success",
        "created_at": "2023-09-09T20:05:48.601Z",
        "updated_at": "2023-09-09T05:09:22.631Z",
        "template_id": "1ef663c0-4dad-4bd3-8a46-e6ed0cf13d6c"
      },
      {
        "id": "8fd0d043-e16d-4421-b2e5-359aea9093ea",
        "content": "What is your biggest fear?",
        "question_topic": "Fear",
        "created_at": "2023-09-09T07:33:21.148Z",
        "updated_at": "2023-09-09T14:44:28.554Z",
        "template_id": "7d86ae4d-19a5-4fbc-b8ec-11011f724b2f"
      },
      {
        "id": "2064d2c7-83fb-45d3-b072-b65a0e9c268d",
        "content": "Tell us about a challenging project you worked on.",
        "question_topic": "Work Experience",
        "created_at": "2023-09-09T04:45:03.259Z",
        "updated_at": "2023-09-09T07:38:41.077Z",
        "template_id": "abcb8bd9-1750-4ac5-965d-b87691a6d7ea"
      },
      {
        "id": "a67b8c43-ec04-4aa5-aae9-9ac1bddbfaff",
        "content": "What are your career goals?",
        "question_topic": "Career Goals",
        "created_at": "2023-09-10T00:38:55.155Z",
        "updated_at": "2023-09-09T10:13:07.933Z",
        "template_id": "1ef663c0-4dad-4bd3-8a46-e6ed0cf13d6c"
      }
    ],
    "roqUser": [
      {
        "reference": "3940a6fb-b80a-4df4-bdb7-789381ae74fa",
        "email": "Edyth17@hotmail.com",
        "firstName": "Annabell",
        "lastName": "Adams",
        "active": true,
        "avatarUrl": "https://cloudflare-ipfs.com/ipfs/Qmd3W5DuhgHirLHGVixi6V76LhCkZUz6pnFt5AJBiyvHye/avatar/685.jpg",
        "tenantId": null
      },
      {
        "reference": "373bcacc-6c4d-45d6-9996-0ce5c46f6af2",
        "email": "Werner72@yahoo.com",
        "firstName": "Wilburn",
        "lastName": "Satterfield",
        "active": true,
        "avatarUrl": "https://avatars.githubusercontent.com/u/84696620",
        "tenantId": null
      },
      {
        "reference": "84aa9d86-47b7-4526-8032-80b1478a6f8d",
        "email": "Kennedy32@gmail.com",
        "firstName": "Jeramy",
        "lastName": "Moen",
        "active": true,
        "avatarUrl": "https://cloudflare-ipfs.com/ipfs/Qmd3W5DuhgHirLHGVixi6V76LhCkZUz6pnFt5AJBiyvHye/avatar/541.jpg",
        "tenantId": null
      },
      {
        "reference": "24c6427d-64dc-4acd-b263-e1f2c5e052dd",
        "email": "Connie28@yahoo.com",
        "firstName": "Quinton",
        "lastName": "Leannon",
        "active": true,
        "avatarUrl": "https://cloudflare-ipfs.com/ipfs/Qmd3W5DuhgHirLHGVixi6V76LhCkZUz6pnFt5AJBiyvHye/avatar/154.jpg",
        "tenantId": null
      },
      {
        "reference": "4c6eedf9-050a-4488-b81b-f05174cc2a70",
        "email": "Jamie30@hotmail.com",
        "firstName": "Blaze",
        "lastName": "Boehm",
        "active": true,
        "avatarUrl": "https://avatars.githubusercontent.com/u/1785809",
        "tenantId": null
      }
    ]
  },
  {
    "topic": [
      {
        "id": "ebc10d20-d682-4b4f-941e-1624bbea9d11",
        "name": "Technology",
        "created_at": "2023-09-10T00:46:46.183Z",
        "updated_at": "2023-09-09T15:39:26.457Z",
        "organization_id": "main_entity_pk"
      },
      {
        "id": "b802c908-faea-48bf-adf0-07eee421d56e",
        "name": "Science",
        "created_at": "2023-09-09T09:00:26.521Z",
        "updated_at": "2023-09-09T15:54:58.627Z",
        "organization_id": "main_entity_pk"
      },
      {
        "id": "981fd0ed-68b1-4a2e-a527-d39a9d63562c",
        "name": "Art",
        "created_at": "2023-09-09T22:53:15.637Z",
        "updated_at": "2023-09-09T20:32:24.549Z",
        "organization_id": "main_entity_pk"
      },
      {
        "id": "32893615-d99c-4540-aae8-a2f85e21ab03",
        "name": "Sports",
        "created_at": "2023-09-09T06:56:54.924Z",
        "updated_at": "2023-09-10T01:19:44.685Z",
        "organization_id": "main_entity_pk"
      },
      {
        "id": "483c548c-b685-44be-bc66-cd96af1175d0",
        "name": "Music",
        "created_at": "2023-09-09T04:36:00.818Z",
        "updated_at": "2023-09-10T00:25:52.968Z",
        "organization_id": "main_entity_pk"
      }
    ],
    "question_generation": [
      {
        "id": "4faf1370-91c9-46ea-9923-d69c89bdc219",
        "number_of_questions": 71526,
        "created_at": "2023-09-10T01:22:03.034Z",
        "updated_at": "2023-09-09T21:23:33.515Z",
        "topic_id": "981fd0ed-68b1-4a2e-a527-d39a9d63562c",
        "user_id": "user_entity_pk"
      },
      {
        "id": "d0c445e6-2fa3-4479-87e9-21276a503288",
        "number_of_questions": 86455,
        "created_at": "2023-09-09T23:30:34.405Z",
        "updated_at": "2023-09-10T00:06:35.470Z",
        "topic_id": "981fd0ed-68b1-4a2e-a527-d39a9d63562c",
        "user_id": "user_entity_pk"
      },
      {
        "id": "a6817187-386c-4e67-b1d8-566c6ed3b905",
        "number_of_questions": 72228,
        "created_at": "2023-09-09T18:48:59.554Z",
        "updated_at": "2023-09-09T18:56:09.058Z",
        "topic_id": "ebc10d20-d682-4b4f-941e-1624bbea9d11",
        "user_id": "user_entity_pk"
      },
      {
        "id": "066a1756-0b9e-4eb8-9516-609c7ecd1af5",
        "number_of_questions": 97436,
        "created_at": "2023-09-09T18:07:30.411Z",
        "updated_at": "2023-09-09T10:54:48.080Z",
        "topic_id": "981fd0ed-68b1-4a2e-a527-d39a9d63562c",
        "user_id": "user_entity_pk"
      },
      {
        "id": "065cdd72-f613-4e59-9ab7-ac2fcf05e862",
        "number_of_questions": 29630,
        "created_at": "2023-09-09T20:22:56.343Z",
        "updated_at": "2023-09-09T04:23:19.927Z",
        "topic_id": "b802c908-faea-48bf-adf0-07eee421d56e",
        "user_id": "user_entity_pk"
      }
    ],
    "template": [
      {
        "id": "c8fdf9aa-3932-4b02-998f-6fd093cd99af",
        "name": "Welcome Email",
        "content": "Dear {firstName}, welcome to our platform!",
        "created_at": "2023-09-09T18:23:03.339Z",
        "updated_at": "2023-09-09T05:40:45.092Z",
        "organization_id": "main_entity_pk"
      },
      {
        "id": "f4184d7c-17ac-4c11-994e-e674f8720eb1",
        "name": "Invoice Template",
        "content": "Please find attached the invoice for your recent purchase.",
        "created_at": "2023-09-09T19:09:47.977Z",
        "updated_at": "2023-09-09T18:09:58.120Z",
        "organization_id": "main_entity_pk"
      },
      {
        "id": "e5c90d96-a3f0-4007-8af5-ad71ac55f178",
        "name": "Event Invitation",
        "content": "You are invited to attend our upcoming event.",
        "created_at": "2023-09-09T05:13:36.386Z",
        "updated_at": "2023-09-10T02:02:29.203Z",
        "organization_id": "main_entity_pk"
      },
      {
        "id": "45bc4241-bffc-433f-980a-aef647218754",
        "name": "Newsletter Template",
        "content": "Check out our latest newsletter for updates.",
        "created_at": "2023-09-09T11:53:18.332Z",
        "updated_at": "2023-09-09T23:41:18.579Z",
        "organization_id": "main_entity_pk"
      },
      {
        "id": "980b8d01-8645-4de8-b4b7-2daa7e253063",
        "name": "Job Application Form",
        "content": "Please fill out the job application form attached.",
        "created_at": "2023-09-09T07:36:13.000Z",
        "updated_at": "2023-09-10T02:21:03.402Z",
        "organization_id": "main_entity_pk"
      }
    ],
    "question": [
      {
        "id": "d2ad9219-9fca-4c06-b5a7-b5b5af2d6782",
        "content": "What is your favorite book?",
        "question_topic": "Books",
        "created_at": "2023-09-10T02:44:47.805Z",
        "updated_at": "2023-09-09T13:16:21.279Z",
        "template_id": "f4184d7c-17ac-4c11-994e-e674f8720eb1"
      },
      {
        "id": "56a20593-c15c-4385-945b-590a75d7252c",
        "content": "How do you define success?",
        "question_topic": "Success",
        "created_at": "2023-09-09T05:39:30.575Z",
        "updated_at": "2023-09-10T01:05:20.484Z",
        "template_id": "980b8d01-8645-4de8-b4b7-2daa7e253063"
      },
      {
        "id": "3249c680-fd2d-4662-9ea9-7d7dd90ca3e7",
        "content": "What is your opinion on climate change?",
        "question_topic": "Climate Change",
        "created_at": "2023-09-10T03:27:24.767Z",
        "updated_at": "2023-09-09T08:00:53.833Z",
        "template_id": "c8fdf9aa-3932-4b02-998f-6fd093cd99af"
      },
      {
        "id": "3a3da181-af61-4179-bd23-43247d6aee12",
        "content": "What motivates you to work hard?",
        "question_topic": "Motivation",
        "created_at": "2023-09-09T09:29:44.014Z",
        "updated_at": "2023-09-09T05:11:43.541Z",
        "template_id": "e5c90d96-a3f0-4007-8af5-ad71ac55f178"
      },
      {
        "id": "9a6cc608-ce9b-43dc-9378-f7b47aec2050",
        "content": "What is your favorite travel destination?",
        "question_topic": "Travel",
        "created_at": "2023-09-09T21:12:15.727Z",
        "updated_at": "2023-09-09T11:14:15.915Z",
        "template_id": "c8fdf9aa-3932-4b02-998f-6fd093cd99af"
      }
    ],
    "roqUser": [
      {
        "reference": "012720f6-cfa6-4af4-b7c7-36f1c184be64",
        "email": "Jarrell_Gleason@hotmail.com",
        "firstName": "Loraine",
        "lastName": "Gleason",
        "active": true,
        "avatarUrl": "https://cloudflare-ipfs.com/ipfs/Qmd3W5DuhgHirLHGVixi6V76LhCkZUz6pnFt5AJBiyvHye/avatar/1031.jpg",
        "tenantId": null
      },
      {
        "reference": "bad576e3-25bb-4452-bb14-0772b511a549",
        "email": "Camila44@yahoo.com",
        "firstName": "Hulda",
        "lastName": "Marks",
        "active": true,
        "avatarUrl": "https://avatars.githubusercontent.com/u/50584305",
        "tenantId": null
      },
      {
        "reference": "edac5da8-843b-47ad-8a52-8703033f0555",
        "email": "Treva.Franey69@hotmail.com",
        "firstName": "Patrick",
        "lastName": "Leannon",
        "active": true,
        "avatarUrl": "https://avatars.githubusercontent.com/u/74640739",
        "tenantId": null
      },
      {
        "reference": "b49a2495-57d7-43b8-8a17-34b01822c91c",
        "email": "Shayna.Nitzsche@hotmail.com",
        "firstName": "Thomas",
        "lastName": "Hackett",
        "active": true,
        "avatarUrl": "https://avatars.githubusercontent.com/u/14083732",
        "tenantId": null
      },
      {
        "reference": "59bc2c0d-1bfb-4cd1-967f-aceb8c787c8a",
        "email": "Jacinthe_Rice55@hotmail.com",
        "firstName": "Salvador",
        "lastName": "Treutel",
        "active": true,
        "avatarUrl": "https://cloudflare-ipfs.com/ipfs/Qmd3W5DuhgHirLHGVixi6V76LhCkZUz6pnFt5AJBiyvHye/avatar/888.jpg",
        "tenantId": null
      }
    ]
  },
  {
    "topic": [
      {
        "id": "8ea76294-5085-4ea4-84c2-cab3055af488",
        "name": "Technology",
        "created_at": "2023-09-09T07:49:18.444Z",
        "updated_at": "2023-09-09T13:58:36.972Z",
        "organization_id": "main_entity_pk"
      },
      {
        "id": "ed19c1df-4229-463f-a2cd-499948cda8ae",
        "name": "Health",
        "created_at": "2023-09-09T05:47:33.245Z",
        "updated_at": "2023-09-09T23:46:17.941Z",
        "organization_id": "main_entity_pk"
      },
      {
        "id": "93e92b5e-542e-487d-9b96-6fd299dfe03f",
        "name": "Education",
        "created_at": "2023-09-09T19:02:22.618Z",
        "updated_at": "2023-09-10T01:04:56.930Z",
        "organization_id": "main_entity_pk"
      },
      {
        "id": "7715bb27-345e-47c4-9706-e283d242a90f",
        "name": "Business",
        "created_at": "2023-09-10T01:10:17.217Z",
        "updated_at": "2023-09-09T16:21:38.281Z",
        "organization_id": "main_entity_pk"
      },
      {
        "id": "37ed4ccb-8076-4aa4-b9fc-e75cfd38a2e1",
        "name": "Science",
        "created_at": "2023-09-10T02:57:19.998Z",
        "updated_at": "2023-09-09T17:38:27.169Z",
        "organization_id": "main_entity_pk"
      }
    ],
    "question_generation": [
      {
        "id": "ac0f264a-dad4-44b9-93f1-9997aa93fb15",
        "number_of_questions": 68076,
        "created_at": "2023-09-09T07:41:41.201Z",
        "updated_at": "2023-09-09T03:51:30.110Z",
        "topic_id": "93e92b5e-542e-487d-9b96-6fd299dfe03f",
        "user_id": "user_entity_pk"
      },
      {
        "id": "184487ee-5523-4c7e-896e-83c36c4f7b8c",
        "number_of_questions": 3211,
        "created_at": "2023-09-10T01:45:29.707Z",
        "updated_at": "2023-09-09T05:59:04.325Z",
        "topic_id": "93e92b5e-542e-487d-9b96-6fd299dfe03f",
        "user_id": "user_entity_pk"
      },
      {
        "id": "22fc1009-7260-4f6d-966e-5b23e9173527",
        "number_of_questions": 37967,
        "created_at": "2023-09-09T04:41:50.055Z",
        "updated_at": "2023-09-09T23:04:31.384Z",
        "topic_id": "ed19c1df-4229-463f-a2cd-499948cda8ae",
        "user_id": "user_entity_pk"
      },
      {
        "id": "47079c76-a3e0-4dea-a878-0f99dca2f0f7",
        "number_of_questions": 40435,
        "created_at": "2023-09-09T19:30:22.019Z",
        "updated_at": "2023-09-09T07:44:48.040Z",
        "topic_id": "ed19c1df-4229-463f-a2cd-499948cda8ae",
        "user_id": "user_entity_pk"
      },
      {
        "id": "d9ee6501-15b7-4bf8-a7f8-54214682acc3",
        "number_of_questions": 78203,
        "created_at": "2023-09-09T21:01:47.796Z",
        "updated_at": "2023-09-10T01:44:31.772Z",
        "topic_id": "7715bb27-345e-47c4-9706-e283d242a90f",
        "user_id": "user_entity_pk"
      }
    ],
    "template": [
      {
        "id": "994f349e-e3b2-4e09-b8c4-6f595649853e",
        "name": "Welcome Email",
        "content": "Thank you for joining us!",
        "created_at": "2023-09-09T21:24:11.678Z",
        "updated_at": "2023-09-09T23:05:27.567Z",
        "organization_id": "main_entity_pk"
      },
      {
        "id": "3c7b7273-604a-4ea8-a4d1-a6fc66003348",
        "name": "Invoice Template",
        "content": "Please find attached the invoice.",
        "created_at": "2023-09-09T08:53:07.460Z",
        "updated_at": "2023-09-09T09:08:25.426Z",
        "organization_id": "main_entity_pk"
      },
      {
        "id": "60dcf4f1-5ecd-4ca6-9a49-5df45b1613d1",
        "name": "Meeting Agenda",
        "content": "Agenda for the upcoming meeting.",
        "created_at": "2023-09-09T14:13:59.471Z",
        "updated_at": "2023-09-09T06:55:53.625Z",
        "organization_id": "main_entity_pk"
      },
      {
        "id": "53bd57f0-44f7-48fa-a527-95705cca4406",
        "name": "Job Application Form",
        "content": "Please fill out the form.",
        "created_at": "2023-09-09T09:54:12.510Z",
        "updated_at": "2023-09-09T14:18:57.069Z",
        "organization_id": "main_entity_pk"
      },
      {
        "id": "cda2f581-c481-4d7f-b682-e79fc1710301",
        "name": "Event Invitation",
        "content": "You're invited to our event!",
        "created_at": "2023-09-09T15:47:26.220Z",
        "updated_at": "2023-09-09T13:05:01.767Z",
        "organization_id": "main_entity_pk"
      }
    ],
    "question": [
      {
        "id": "cc670f07-3f08-40db-84d9-9a51321cd7db",
        "content": "What is your favorite book?",
        "question_topic": "Personal Development",
        "created_at": "2023-09-09T05:48:34.638Z",
        "updated_at": "2023-09-09T10:24:45.625Z",
        "template_id": "60dcf4f1-5ecd-4ca6-9a49-5df45b1613d1"
      },
      {
        "id": "7006b0f3-4307-444c-96bb-142b5da0e989",
        "content": "How do you define success?",
        "question_topic": "Career Growth",
        "created_at": "2023-09-09T10:51:17.637Z",
        "updated_at": "2023-09-09T13:07:27.178Z",
        "template_id": "53bd57f0-44f7-48fa-a527-95705cca4406"
      },
      {
        "id": "a30eb386-13b0-4c62-b652-12d4bbed0032",
        "content": "What is your biggest fear?",
        "question_topic": "Fear and Anxiety",
        "created_at": "2023-09-09T11:08:20.734Z",
        "updated_at": "2023-09-09T18:56:14.354Z",
        "template_id": "60dcf4f1-5ecd-4ca6-9a49-5df45b1613d1"
      },
      {
        "id": "fc1807af-a142-4c8e-92fb-23267054ba35",
        "content": "What motivates you?",
        "question_topic": "Motivation",
        "created_at": "2023-09-09T18:12:50.153Z",
        "updated_at": "2023-09-10T01:20:31.270Z",
        "template_id": "cda2f581-c481-4d7f-b682-e79fc1710301"
      },
      {
        "id": "6d4410ba-8e18-4511-a23f-1cc9f3782627",
        "content": "What is your favorite hobby?",
        "question_topic": "Hobbies and Interests",
        "created_at": "2023-09-10T03:36:54.223Z",
        "updated_at": "2023-09-09T14:27:30.108Z",
        "template_id": "cda2f581-c481-4d7f-b682-e79fc1710301"
      }
    ],
    "roqUser": [
      {
        "reference": "f9ed0183-2bb8-4806-b6f4-bf3c6920c2e6",
        "email": "Edyth_Hackett@yahoo.com",
        "firstName": "Josefa",
        "lastName": "Bradtke-Ernser",
        "active": true,
        "avatarUrl": "https://avatars.githubusercontent.com/u/41811992",
        "tenantId": null
      },
      {
        "reference": "614c0d77-382e-40f8-ac6d-2aaee1e0d6bc",
        "email": "Magali3@hotmail.com",
        "firstName": "Fern",
        "lastName": "Spinka",
        "active": true,
        "avatarUrl": "https://cloudflare-ipfs.com/ipfs/Qmd3W5DuhgHirLHGVixi6V76LhCkZUz6pnFt5AJBiyvHye/avatar/715.jpg",
        "tenantId": null
      },
      {
        "reference": "2e03683d-b6d0-4fa4-b4c8-eb7d4447d106",
        "email": "Kelvin_Abbott@hotmail.com",
        "firstName": "Norbert",
        "lastName": "Oberbrunner",
        "active": true,
        "avatarUrl": "https://cloudflare-ipfs.com/ipfs/Qmd3W5DuhgHirLHGVixi6V76LhCkZUz6pnFt5AJBiyvHye/avatar/1086.jpg",
        "tenantId": null
      },
      {
        "reference": "68778ee4-19fc-4970-9153-e20878466810",
        "email": "Michale87@hotmail.com",
        "firstName": "Eriberto",
        "lastName": "Abernathy",
        "active": true,
        "avatarUrl": "https://avatars.githubusercontent.com/u/55267559",
        "tenantId": null
      },
      {
        "reference": "f89cbbd8-4f00-4bdd-ac6a-dd1761dace1a",
        "email": "Woodrow.Shanahan37@hotmail.com",
        "firstName": "Giles",
        "lastName": "Dooley",
        "active": true,
        "avatarUrl": "https://cloudflare-ipfs.com/ipfs/Qmd3W5DuhgHirLHGVixi6V76LhCkZUz6pnFt5AJBiyvHye/avatar/193.jpg",
        "tenantId": null
      }
    ]
  },
  {
    "topic": [
      {
        "id": "e5515bc8-92b9-4a3b-8d0e-b2dead3a1210",
        "name": "Technology",
        "created_at": "2023-09-09T10:09:03.186Z",
        "updated_at": "2023-09-09T18:29:21.431Z",
        "organization_id": "main_entity_pk"
      },
      {
        "id": "b01964aa-d7b9-4b6c-bf78-fb42cfe92979",
        "name": "Environment",
        "created_at": "2023-09-09T08:38:47.432Z",
        "updated_at": "2023-09-09T22:35:53.389Z",
        "organization_id": "main_entity_pk"
      },
      {
        "id": "f7974986-96b8-43c2-8278-6e1b942d5b8a",
        "name": "Business",
        "created_at": "2023-09-09T23:34:11.890Z",
        "updated_at": "2023-09-09T09:11:29.608Z",
        "organization_id": "main_entity_pk"
      },
      {
        "id": "a392632e-3231-4b7c-a3c3-0fa570dc6d85",
        "name": "Healthcare",
        "created_at": "2023-09-09T10:37:59.006Z",
        "updated_at": "2023-09-09T17:43:13.736Z",
        "organization_id": "main_entity_pk"
      },
      {
        "id": "26af04ee-0166-49fa-8c2a-7b34af17d8c1",
        "name": "Education",
        "created_at": "2023-09-09T19:32:50.800Z",
        "updated_at": "2023-09-09T14:40:33.523Z",
        "organization_id": "main_entity_pk"
      }
    ],
    "question_generation": [
      {
        "id": "387dcab1-8722-48e4-864b-3ac1b3caff40",
        "number_of_questions": 56731,
        "created_at": "2023-09-09T15:52:36.775Z",
        "updated_at": "2023-09-09T17:06:05.966Z",
        "topic_id": "a392632e-3231-4b7c-a3c3-0fa570dc6d85",
        "user_id": "user_entity_pk"
      },
      {
        "id": "6d4d8d73-b2c8-4687-9219-5704d5a4189a",
        "number_of_questions": 10735,
        "created_at": "2023-09-09T12:14:16.674Z",
        "updated_at": "2023-09-09T13:01:00.343Z",
        "topic_id": "e5515bc8-92b9-4a3b-8d0e-b2dead3a1210",
        "user_id": "user_entity_pk"
      },
      {
        "id": "511263c3-bea4-4ee3-8202-31c02544e926",
        "number_of_questions": 69543,
        "created_at": "2023-09-10T01:41:43.235Z",
        "updated_at": "2023-09-09T17:48:44.317Z",
        "topic_id": "b01964aa-d7b9-4b6c-bf78-fb42cfe92979",
        "user_id": "user_entity_pk"
      },
      {
        "id": "c192e7f0-0f27-4b64-9f8b-c43980595337",
        "number_of_questions": 30079,
        "created_at": "2023-09-09T23:52:34.601Z",
        "updated_at": "2023-09-09T08:25:00.202Z",
        "topic_id": "b01964aa-d7b9-4b6c-bf78-fb42cfe92979",
        "user_id": "user_entity_pk"
      },
      {
        "id": "ba875a7d-cad8-4b20-a5cf-7934b55d2a57",
        "number_of_questions": 15575,
        "created_at": "2023-09-09T05:24:57.020Z",
        "updated_at": "2023-09-10T03:16:20.693Z",
        "topic_id": "b01964aa-d7b9-4b6c-bf78-fb42cfe92979",
        "user_id": "user_entity_pk"
      }
    ],
    "template": [
      {
        "id": "7101ac59-3ed6-4638-921f-31e8ce2a55b2",
        "name": "Welcome Email",
        "content": "Dear [firstName],\n\nThank you for joining our platform!\n\nBest regards,\n[organizationName]",
        "created_at": "2023-09-09T15:12:52.114Z",
        "updated_at": "2023-09-09T09:19:14.252Z",
        "organization_id": "main_entity_pk"
      },
      {
        "id": "0e93343b-52b8-450b-8956-8caad8006fba",
        "name": "Invoice Template",
        "content": "Invoice Number: [invoiceNumber]\n\nItem\t\t\tQuantity\t\tPrice\n\n[productName]\t\t[quantity]\t\t\t[price]",
        "created_at": "2023-09-09T06:06:07.924Z",
        "updated_at": "2023-09-09T04:18:16.891Z",
        "organization_id": "main_entity_pk"
      },
      {
        "id": "4de9a0df-9a97-484d-8904-86f2ede6eae2",
        "name": "Meeting Agenda",
        "content": "Meeting Agenda\n\nDate: [meetingDate]\nTime: [meetingTime]\nLocation: [meetingLocation]\n\nAgenda:\n1. [agendaItem1]\n2. [agendaItem2]\n3. [agendaItem3]",
        "created_at": "2023-09-09T17:35:54.901Z",
        "updated_at": "2023-09-09T06:45:09.144Z",
        "organization_id": "main_entity_pk"
      },
      {
        "id": "291a2087-ec0b-41e2-aafd-2fa7ea58a714",
        "name": "Job Application Form",
        "content": "Job Application Form\n\nPersonal Information:\n- Full Name: [fullName]\n- Email: [email]\n- Phone Number: [phoneNumber]\n\n[additionalFields]",
        "created_at": "2023-09-09T11:47:04.884Z",
        "updated_at": "2023-09-09T05:56:50.532Z",
        "organization_id": "main_entity_pk"
      },
      {
        "id": "60afb6eb-e608-4176-b6a9-2b2d623e003e",
        "name": "Product Catalog",
        "content": "Product Catalog\n\nCategory: [category]\n\nProduct\t\t\tPrice\n\n[productName1]\t\t[price1]\n[productName2]\t\t[price2]\n[productName3]\t\t[price3]",
        "created_at": "2023-09-09T13:55:18.596Z",
        "updated_at": "2023-09-09T08:23:18.257Z",
        "organization_id": "main_entity_pk"
      }
    ],
    "question": [
      {
        "id": "ac3e5351-09c0-493e-b728-fde6abda5b9f",
        "content": "What is your favorite book?",
        "question_topic": "Personal Preferences",
        "created_at": "2023-09-09T06:48:14.337Z",
        "updated_at": "2023-09-09T21:11:31.308Z",
        "template_id": "60afb6eb-e608-4176-b6a9-2b2d623e003e"
      },
      {
        "id": "8e511167-6f38-465a-831c-b883ff484519",
        "content": "How do you define success?",
        "question_topic": "Career Development",
        "created_at": "2023-09-09T04:26:30.035Z",
        "updated_at": "2023-09-10T01:40:50.160Z",
        "template_id": "0e93343b-52b8-450b-8956-8caad8006fba"
      },
      {
        "id": "7cc5a663-1acc-4aff-bf56-d401e83b7cf1",
        "content": "What is your favorite travel destination?",
        "question_topic": "Travel Experiences",
        "created_at": "2023-09-09T20:47:38.095Z",
        "updated_at": "2023-09-09T20:42:49.403Z",
        "template_id": "0e93343b-52b8-450b-8956-8caad8006fba"
      },
      {
        "id": "d33fe03c-ac10-447d-9160-e0d9386767b3",
        "content": "What is your go-to comfort food?",
        "question_topic": "Food Choices",
        "created_at": "2023-09-09T17:34:37.545Z",
        "updated_at": "2023-09-09T19:03:47.680Z",
        "template_id": "4de9a0df-9a97-484d-8904-86f2ede6eae2"
      },
      {
        "id": "e9cdf4f3-7088-483f-83aa-cd4eefa6fe1f",
        "content": "What is your dream job?",
        "question_topic": "Professional Aspirations",
        "created_at": "2023-09-09T11:37:39.999Z",
        "updated_at": "2023-09-09T11:22:59.138Z",
        "template_id": "291a2087-ec0b-41e2-aafd-2fa7ea58a714"
      }
    ],
    "roqUser": [
      {
        "reference": "12527259-dfb5-4f74-9c2d-0ecbeae87e08",
        "email": "Sarina25@hotmail.com",
        "firstName": "Luz",
        "lastName": "Hettinger",
        "active": true,
        "avatarUrl": "https://avatars.githubusercontent.com/u/53610553",
        "tenantId": null
      },
      {
        "reference": "bc1ba6bf-4396-48c1-a213-98895953c578",
        "email": "Monique.Mertz@hotmail.com",
        "firstName": "Noble",
        "lastName": "Beatty",
        "active": true,
        "avatarUrl": "https://cloudflare-ipfs.com/ipfs/Qmd3W5DuhgHirLHGVixi6V76LhCkZUz6pnFt5AJBiyvHye/avatar/74.jpg",
        "tenantId": null
      },
      {
        "reference": "f5cb36e4-9dd2-4901-bc24-6e645f4da144",
        "email": "Kaden.Leuschke@yahoo.com",
        "firstName": "Gust",
        "lastName": "Pouros",
        "active": true,
        "avatarUrl": "https://avatars.githubusercontent.com/u/80999253",
        "tenantId": null
      },
      {
        "reference": "434f43d1-a219-4ce2-8122-caa56a580c16",
        "email": "Ahmad_Gutkowski23@gmail.com",
        "firstName": "Gwendolyn",
        "lastName": "Aufderhar",
        "active": true,
        "avatarUrl": "https://cloudflare-ipfs.com/ipfs/Qmd3W5DuhgHirLHGVixi6V76LhCkZUz6pnFt5AJBiyvHye/avatar/76.jpg",
        "tenantId": null
      },
      {
        "reference": "ba4946fa-538b-417b-a39e-c70fa404096a",
        "email": "Delilah95@gmail.com",
        "firstName": "Al",
        "lastName": "Kunze",
        "active": true,
        "avatarUrl": "https://avatars.githubusercontent.com/u/86988811",
        "tenantId": null
      }
    ]
  },
  {
    "topic": [
      {
        "id": "482e0c54-5cb8-4d40-bcb9-c547dcec620c",
        "name": "Technology",
        "created_at": "2023-09-09T20:56:30.658Z",
        "updated_at": "2023-09-09T06:23:32.499Z",
        "organization_id": "main_entity_pk"
      },
      {
        "id": "8aa325ac-04d5-4cf8-acbe-8df854698919",
        "name": "Environment",
        "created_at": "2023-09-09T22:57:46.733Z",
        "updated_at": "2023-09-09T06:27:42.216Z",
        "organization_id": "main_entity_pk"
      },
      {
        "id": "4402750b-2e62-4c97-99ba-e9884997804f",
        "name": "Healthcare",
        "created_at": "2023-09-09T22:46:20.224Z",
        "updated_at": "2023-09-09T06:11:04.073Z",
        "organization_id": "main_entity_pk"
      },
      {
        "id": "bb2c7403-818e-4456-8082-94c73fb2d89a",
        "name": "Education",
        "created_at": "2023-09-09T09:59:56.070Z",
        "updated_at": "2023-09-09T19:41:04.080Z",
        "organization_id": "main_entity_pk"
      },
      {
        "id": "88038052-838c-4254-8237-40adbf6163a0",
        "name": "Fashion",
        "created_at": "2023-09-09T17:33:30.916Z",
        "updated_at": "2023-09-10T03:30:16.076Z",
        "organization_id": "main_entity_pk"
      }
    ],
    "question_generation": [
      {
        "id": "d863adf2-e4d4-4891-b0dd-468888bae4c4",
        "number_of_questions": 10614,
        "created_at": "2023-09-09T14:31:31.412Z",
        "updated_at": "2023-09-09T17:38:05.506Z",
        "topic_id": "88038052-838c-4254-8237-40adbf6163a0",
        "user_id": "user_entity_pk"
      },
      {
        "id": "d8240107-0e5f-4007-89de-603d289e1fe0",
        "number_of_questions": 7447,
        "created_at": "2023-09-09T22:16:24.791Z",
        "updated_at": "2023-09-09T23:23:19.148Z",
        "topic_id": "482e0c54-5cb8-4d40-bcb9-c547dcec620c",
        "user_id": "user_entity_pk"
      },
      {
        "id": "4e0b7f15-a2d5-47de-be5f-2724cb521a2e",
        "number_of_questions": 97299,
        "created_at": "2023-09-09T04:24:15.311Z",
        "updated_at": "2023-09-09T20:41:06.489Z",
        "topic_id": "88038052-838c-4254-8237-40adbf6163a0",
        "user_id": "user_entity_pk"
      },
      {
        "id": "e782f80d-730a-41c2-85c9-ca6f74f01144",
        "number_of_questions": 9154,
        "created_at": "2023-09-09T20:08:31.039Z",
        "updated_at": "2023-09-09T13:10:05.177Z",
        "topic_id": "bb2c7403-818e-4456-8082-94c73fb2d89a",
        "user_id": "user_entity_pk"
      },
      {
        "id": "1eda82fa-eba0-4009-8793-47b7695e6bfb",
        "number_of_questions": 50676,
        "created_at": "2023-09-10T01:32:28.342Z",
        "updated_at": "2023-09-09T15:17:07.817Z",
        "topic_id": "bb2c7403-818e-4456-8082-94c73fb2d89a",
        "user_id": "user_entity_pk"
      }
    ],
    "template": [
      {
        "id": "1a6e8bc5-11ba-4080-8915-12c490c1bae6",
        "name": "Welcome Email",
        "content": "Dear [First Name],\n\nWe are delighted to welcome you to our community. Please find attached the necessary information for getting started.\n\nBest regards,\n[Organization Name]",
        "created_at": "2023-09-09T18:13:09.339Z",
        "updated_at": "2023-09-09T21:29:14.514Z",
        "organization_id": "main_entity_pk"
      },
      {
        "id": "93f18313-13a3-408f-b218-ae471cc69acb",
        "name": "Invoice",
        "content": "Invoice Number: [Invoice Number]\n\nDear [Customer Name],\n\nThank you for your recent purchase. Please find attached the invoice for your reference.\n\nSincerely,\n[Organization Name]",
        "created_at": "2023-09-09T11:56:21.486Z",
        "updated_at": "2023-09-09T08:18:07.682Z",
        "organization_id": "main_entity_pk"
      },
      {
        "id": "39b39921-dc2b-4a03-a63a-0ad443c34d33",
        "name": "Meeting Agenda",
        "content": "Meeting Agenda\n\nDate: [Meeting Date]\nTime: [Meeting Time]\nLocation: [Meeting Location]\n\nAgenda:\n1. Introduction\n2. Discussion on [Topic]\n3. Action Items\n\nBest regards,\n[Meeting Organizer]",
        "created_at": "2023-09-09T08:51:22.109Z",
        "updated_at": "2023-09-09T18:00:18.914Z",
        "organization_id": "main_entity_pk"
      },
      {
        "id": "e6f92622-c152-453a-a6c9-153efa046220",
        "name": "Job Application",
        "content": "Dear Hiring Manager,\n\nI am writing to express my interest in the [Job Title] position at [Organization Name]. Please find attached my resume for your consideration.\n\nThank you,\n[Applicant Name]",
        "created_at": "2023-09-10T02:07:56.803Z",
        "updated_at": "2023-09-09T22:41:57.539Z",
        "organization_id": "main_entity_pk"
      },
      {
        "id": "8f53e20c-a5a9-49d2-86ae-94a00cde12db",
        "name": "Event Invitation",
        "content": "You're Invited!\n\nEvent: [Event Name]\nDate: [Event Date]\nTime: [Event Time]\nLocation: [Event Location]\n\nWe look forward to seeing you there!\n\nBest regards,\n[Event Organizer]",
        "created_at": "2023-09-09T09:13:23.706Z",
        "updated_at": "2023-09-09T11:11:41.178Z",
        "organization_id": "main_entity_pk"
      }
    ],
    "question": [
      {
        "id": "8ba0cdee-2b46-496c-b3c0-0bf10785493a",
        "content": "What are the benefits of using artificial intelligence in healthcare?",
        "question_topic": "Technology",
        "created_at": "2023-09-09T08:24:03.517Z",
        "updated_at": "2023-09-09T19:26:36.548Z",
        "template_id": "1a6e8bc5-11ba-4080-8915-12c490c1bae6"
      },
      {
        "id": "9e5c56f7-0434-4c93-afae-69ef52a38a3e",
        "content": "How can we reduce plastic waste in our daily lives?",
        "question_topic": "Environment",
        "created_at": "2023-09-09T23:11:10.574Z",
        "updated_at": "2023-09-09T06:49:39.515Z",
        "template_id": "93f18313-13a3-408f-b218-ae471cc69acb"
      },
      {
        "id": "cc6e0996-ff09-4959-8218-79ef86650f42",
        "content": "What strategies can schools implement to improve student engagement?",
        "question_topic": "Education",
        "created_at": "2023-09-09T09:27:17.651Z",
        "updated_at": "2023-09-09T11:02:35.845Z",
        "template_id": "1a6e8bc5-11ba-4080-8915-12c490c1bae6"
      },
      {
        "id": "8f0257a6-4eca-4cd6-b8c8-502c9db6d52d",
        "content": "What are the latest fashion trends for the upcoming season?",
        "question_topic": "Fashion",
        "created_at": "2023-09-09T16:54:01.903Z",
        "updated_at": "2023-09-09T13:09:15.265Z",
        "template_id": "e6f92622-c152-453a-a6c9-153efa046220"
      },
      {
        "id": "e6be7fb5-ccfa-4299-a71e-29526b7910fc",
        "content": "How can we promote renewable energy sources in our community?",
        "question_topic": "Renewable Energy",
        "created_at": "2023-09-09T09:26:56.509Z",
        "updated_at": "2023-09-10T00:43:28.917Z",
        "template_id": "93f18313-13a3-408f-b218-ae471cc69acb"
      }
    ],
    "roqUser": [
      {
        "reference": "5aafaed7-9f91-46c1-b1c9-e46ca62ff6fb",
        "email": "Steve18@yahoo.com",
        "firstName": "Bennett",
        "lastName": "MacGyver",
        "active": true,
        "avatarUrl": "https://avatars.githubusercontent.com/u/78996199",
        "tenantId": null
      },
      {
        "reference": "63dcea5b-e780-4853-9d26-c7fd8447d66f",
        "email": "Waino92@hotmail.com",
        "firstName": "Velva",
        "lastName": "Rogahn",
        "active": true,
        "avatarUrl": "https://cloudflare-ipfs.com/ipfs/Qmd3W5DuhgHirLHGVixi6V76LhCkZUz6pnFt5AJBiyvHye/avatar/595.jpg",
        "tenantId": null
      },
      {
        "reference": "4ae76323-40d8-46ab-be3a-dc1cb324cadf",
        "email": "Jamal.Mueller@hotmail.com",
        "firstName": "Barney",
        "lastName": "Osinski",
        "active": true,
        "avatarUrl": "https://cloudflare-ipfs.com/ipfs/Qmd3W5DuhgHirLHGVixi6V76LhCkZUz6pnFt5AJBiyvHye/avatar/495.jpg",
        "tenantId": null
      },
      {
        "reference": "642d388e-f41f-4fdb-9fe8-e645c41f71f9",
        "email": "Laila_Kerluke@gmail.com",
        "firstName": "Eveline",
        "lastName": "Crist",
        "active": true,
        "avatarUrl": "https://avatars.githubusercontent.com/u/81824152",
        "tenantId": null
      },
      {
        "reference": "9b0f972e-bdff-4d13-a52c-e64df9ce5e3b",
        "email": "Maya.Kautzer12@yahoo.com",
        "firstName": "Kay",
        "lastName": "Bashirian",
        "active": true,
        "avatarUrl": "https://cloudflare-ipfs.com/ipfs/Qmd3W5DuhgHirLHGVixi6V76LhCkZUz6pnFt5AJBiyvHye/avatar/795.jpg",
        "tenantId": null
      }
    ]
  },
  {
    "topic": [
      {
        "id": "11c2badf-c353-4365-aaf9-b3b6465b23ae",
        "name": "Technology",
        "created_at": "2023-09-09T23:52:09.609Z",
        "updated_at": "2023-09-09T20:22:48.695Z",
        "organization_id": "main_entity_pk"
      },
      {
        "id": "364e1ea3-988d-4b65-a792-695f76054166",
        "name": "Environment",
        "created_at": "2023-09-09T09:08:36.726Z",
        "updated_at": "2023-09-09T12:45:27.775Z",
        "organization_id": "main_entity_pk"
      },
      {
        "id": "cee20da0-2d73-4812-9347-6aa53a6b460b",
        "name": "Business",
        "created_at": "2023-09-09T19:23:56.836Z",
        "updated_at": "2023-09-09T07:39:40.434Z",
        "organization_id": "main_entity_pk"
      },
      {
        "id": "14aff28b-6d0b-443e-abf3-511df543eea0",
        "name": "Healthcare",
        "created_at": "2023-09-09T18:42:28.556Z",
        "updated_at": "2023-09-09T18:04:54.069Z",
        "organization_id": "main_entity_pk"
      },
      {
        "id": "18c40534-d992-4880-9123-40b2e9724ab3",
        "name": "Fashion",
        "created_at": "2023-09-10T02:49:36.829Z",
        "updated_at": "2023-09-09T19:57:00.444Z",
        "organization_id": "main_entity_pk"
      }
    ],
    "question_generation": [
      {
        "id": "a3d6ce86-bf32-4b5b-a0a2-451fa8ceec4c",
        "number_of_questions": 72544,
        "created_at": "2023-09-10T02:53:19.061Z",
        "updated_at": "2023-09-09T09:03:15.400Z",
        "topic_id": "cee20da0-2d73-4812-9347-6aa53a6b460b",
        "user_id": "user_entity_pk"
      },
      {
        "id": "23d696d6-2837-4a9a-b752-ae5f273cfb0e",
        "number_of_questions": 33681,
        "created_at": "2023-09-09T23:10:11.151Z",
        "updated_at": "2023-09-09T20:47:30.987Z",
        "topic_id": "cee20da0-2d73-4812-9347-6aa53a6b460b",
        "user_id": "user_entity_pk"
      },
      {
        "id": "89e4b733-7af5-4fe2-9046-08d8244e8613",
        "number_of_questions": 19259,
        "created_at": "2023-09-10T03:10:08.434Z",
        "updated_at": "2023-09-09T10:45:29.806Z",
        "topic_id": "18c40534-d992-4880-9123-40b2e9724ab3",
        "user_id": "user_entity_pk"
      },
      {
        "id": "e66c7ef8-e9b6-44c9-910c-10f1f547364e",
        "number_of_questions": 9443,
        "created_at": "2023-09-09T13:51:08.858Z",
        "updated_at": "2023-09-09T12:31:56.487Z",
        "topic_id": "cee20da0-2d73-4812-9347-6aa53a6b460b",
        "user_id": "user_entity_pk"
      },
      {
        "id": "833df769-9b59-448b-973d-6cdb4794207d",
        "number_of_questions": 63396,
        "created_at": "2023-09-10T01:05:16.938Z",
        "updated_at": "2023-09-10T01:48:09.500Z",
        "topic_id": "18c40534-d992-4880-9123-40b2e9724ab3",
        "user_id": "user_entity_pk"
      }
    ],
    "template": [
      {
        "id": "6dfb1aa0-7a1b-44c6-999b-3330b544e40a",
        "name": "Welcome Email",
        "content": "Dear [FirstName],\n\nWelcome to our platform!",
        "created_at": "2023-09-09T18:31:39.636Z",
        "updated_at": "2023-09-09T22:18:14.176Z",
        "organization_id": "main_entity_pk"
      },
      {
        "id": "4814197a-5ddb-4f02-8cea-18fcc132fcb1",
        "name": "Invoice Template",
        "content": "Invoice Number: [InvoiceNumber]\n\nTotal Amount Due: [AmountDue]",
        "created_at": "2023-09-09T16:44:38.630Z",
        "updated_at": "2023-09-09T12:56:27.355Z",
        "organization_id": "main_entity_pk"
      },
      {
        "id": "20236bf9-7a73-4422-913d-d2907dfc46ed",
        "name": "Meeting Agenda",
        "content": "Agenda for the meeting on [MeetingDate] at [MeetingTime]",
        "created_at": "2023-09-09T14:54:46.710Z",
        "updated_at": "2023-09-09T05:33:02.305Z",
        "organization_id": "main_entity_pk"
      },
      {
        "id": "ba9e464c-bb7d-47b3-9790-3e5a3c0b7afe",
        "name": "Product Launch Announcement",
        "content": "Join us for the exciting launch of our new product on [LaunchDate]!",
        "created_at": "2023-09-10T00:14:23.762Z",
        "updated_at": "2023-09-09T11:38:03.511Z",
        "organization_id": "main_entity_pk"
      },
      {
        "id": "6751df61-2411-458d-be56-867b1685b001",
        "name": "Job Application Form",
        "content": "Please fill out the following form to apply for the position:\n\n[FormFields]",
        "created_at": "2023-09-10T01:35:20.521Z",
        "updated_at": "2023-09-09T20:14:51.906Z",
        "organization_id": "main_entity_pk"
      }
    ],
    "question": [
      {
        "id": "acfbdef7-cabb-4690-9db3-ff52fc2fbf5c",
        "content": "What are your thoughts on the latest technological advancements?",
        "question_topic": "Technology",
        "created_at": "2023-09-09T22:37:26.442Z",
        "updated_at": "2023-09-10T01:11:00.568Z",
        "template_id": "6dfb1aa0-7a1b-44c6-999b-3330b544e40a"
      },
      {
        "id": "c40ebe32-9db6-41e1-ac77-1cb7b8e913e9",
        "content": "How can we improve our environmental sustainability efforts?",
        "question_topic": "Environment",
        "created_at": "2023-09-09T15:37:45.120Z",
        "updated_at": "2023-09-09T21:46:19.475Z",
        "template_id": "20236bf9-7a73-4422-913d-d2907dfc46ed"
      },
      {
        "id": "6d2a583d-d023-48d4-ae7b-3a7351f117c5",
        "content": "What strategies would you recommend for business growth?",
        "question_topic": "Business",
        "created_at": "2023-09-09T05:40:58.542Z",
        "updated_at": "2023-09-10T02:54:11.550Z",
        "template_id": "20236bf9-7a73-4422-913d-d2907dfc46ed"
      },
      {
        "id": "65019533-c7e2-456f-9607-92b92af499f3",
        "content": "How can we enhance patient experience in healthcare?",
        "question_topic": "Healthcare",
        "created_at": "2023-09-10T02:12:29.749Z",
        "updated_at": "2023-09-09T22:35:02.146Z",
        "template_id": "6751df61-2411-458d-be56-867b1685b001"
      },
      {
        "id": "23862d53-8aa0-4792-99a7-f9e69290a2ef",
        "content": "What sustainable materials can be used in fashion design?",
        "question_topic": "Fashion",
        "created_at": "2023-09-09T09:01:05.630Z",
        "updated_at": "2023-09-09T14:01:20.938Z",
        "template_id": "6dfb1aa0-7a1b-44c6-999b-3330b544e40a"
      }
    ],
    "roqUser": [
      {
        "reference": "7e26fb88-c3dd-48ae-8b79-ba33759c96dc",
        "email": "Koby22@gmail.com",
        "firstName": "Koby",
        "lastName": "McKenzie",
        "active": true,
        "avatarUrl": "https://avatars.githubusercontent.com/u/65489941",
        "tenantId": null
      },
      {
        "reference": "4e375646-ca24-43af-a7f3-cd32ae115c2c",
        "email": "Ali.Crona-Marvin70@gmail.com",
        "firstName": "Estell",
        "lastName": "Marquardt",
        "active": true,
        "avatarUrl": "https://cloudflare-ipfs.com/ipfs/Qmd3W5DuhgHirLHGVixi6V76LhCkZUz6pnFt5AJBiyvHye/avatar/916.jpg",
        "tenantId": null
      },
      {
        "reference": "0c8b86f2-ddba-423a-8afb-376fe7cd98e3",
        "email": "Geoffrey_Kub69@hotmail.com",
        "firstName": "Keshaun",
        "lastName": "Zemlak",
        "active": true,
        "avatarUrl": "https://cloudflare-ipfs.com/ipfs/Qmd3W5DuhgHirLHGVixi6V76LhCkZUz6pnFt5AJBiyvHye/avatar/70.jpg",
        "tenantId": null
      },
      {
        "reference": "c4dfc30a-57e8-419f-938f-f5d8b6cee5ed",
        "email": "Geraldine.Auer53@hotmail.com",
        "firstName": "Dawn",
        "lastName": "Schultz",
        "active": true,
        "avatarUrl": "https://avatars.githubusercontent.com/u/41536857",
        "tenantId": null
      },
      {
        "reference": "3fb654c5-11e0-4ad0-b6ca-49a75733076a",
        "email": "Berneice_Balistreri@hotmail.com",
        "firstName": "Antwan",
        "lastName": "Lebsack",
        "active": true,
        "avatarUrl": "https://cloudflare-ipfs.com/ipfs/Qmd3W5DuhgHirLHGVixi6V76LhCkZUz6pnFt5AJBiyvHye/avatar/5.jpg",
        "tenantId": null
      }
    ]
  }
]
